anys/__init__.py
anys/py.typed
anys-0.3.1.dist-info/METADATA
anys-0.3.1.dist-info/WHEEL
anys-0.3.1.dist-info/licenses/LICENSE
anys-0.3.1.dist-info/RECORD
