Metadata-Version: 2.3
Name: anys
Version: 0.3.1
Summary: Matchers for pytest
Project-URL: Source Code, https://github.com/jwodder/anys
Project-URL: Bug Tracker, https://github.com/jwodder/anys/issues
Author-email: John Thorvald Wodder II <anys@varonathe.org>
License: MIT
Keywords: comparison,matchers,pytest,testing,unit test
Classifier: Intended Audience :: Developers
Classifier: License :: OSI Approved :: MIT License
Classifier: Programming Language :: Python :: 3
Classifier: Programming Language :: Python :: 3 :: Only
Classifier: Programming Language :: Python :: 3.8
Classifier: Programming Language :: Python :: 3.9
Classifier: Programming Language :: Python :: 3.10
Classifier: Programming Language :: Python :: 3.11
Classifier: Programming Language :: Python :: 3.12
Classifier: Programming Language :: Python :: 3.13
Classifier: Programming Language :: Python :: Implementation :: CPython
Classifier: Programming Language :: Python :: Implementation :: PyPy
Classifier: Topic :: Software Development :: Testing
Classifier: Topic :: Software Development :: Testing :: Unit
Classifier: Typing :: Typed
Requires-Python: >=3.8
